[
  {
    "concello_codigo": "15030",
    "concello_nome": "Coruña (A)",
    "ensinanzas": [
      {
        "codigo": "24",
        "nome": "Educación secundaria obrigatoria"
      },
      {
        "codigo": "29",
        "nome": "Bacharelato"
      },
      {
        "codigo": "22",
        "nome": "Educación infantil"
      },
      {
        "codigo": "25",
        "nome": "Educación primaria"
      }
    ]
  },
  {
    "concello_codigo": "15036",
    "concello_nome": "Ferrol",
    "ensinanzas": [
      {
        "codigo": "22",
        "nome": "Educación infantil"
      },
      {
        "codigo": "25",
        "nome": "Educación primaria"
      },
      {
        "codigo": "29",
        "nome": "Bacharelato"
      },
      {
        "codigo": "24",
        "nome": "Educación secundaria obrigatoria"
      }
    ]
  },
  {
    "concello_codigo": "15078",
    "concello_nome": "Santiago de Compostela",
    "ensinanzas": [
      {
        "codigo": "22",
        "nome": "Educación infantil"
      },
      {
        "codigo": "29",
        "nome": "Bacharelato"
      },
      {
        "codigo": "24",
        "nome": "Educación secundaria obrigatoria"
      },
      {
        "codigo": "25",
        "nome": "Educación primaria"
      }
    ]
  }
]